journal_prompts/__init__.py
journal_prompts/dto/__init__.py
journal_prompts/dto/journal_prompts_500_kb.py
journal_prompts/dto/journal_prompts_random_kb.py
journal_prompts/dto/random_questions_kb.py
journal_prompts/dto/sarcastic_questions_kb.py
journal_prompts/svc/__init__.py
journal_prompts/svc/find_random_question.py
journal_prompts-0.1.7.dist-info/WHEEL
journal_prompts-0.1.7.dist-info/METADATA
journal_prompts-0.1.7.dist-info/RECORD
